once_pkg/__init__.py
once_pkg/main.py
suhengshuo-0.0.1.dist-info/LICENSE.txt
suhengshuo-0.0.1.dist-info/METADATA
suhengshuo-0.0.1.dist-info/WHEEL
suhengshuo-0.0.1.dist-info/top_level.txt
suhengshuo-0.0.1.dist-info/RECORD
