Metadata-Version: 2.1
Name: suhengshuo
Version: 0.0.1
Summary: A hello word
Home-page: https://github.com/suhengshuo/pip
Author: suhengshuo
Author-email: 12323@qq.com
Classifier: Programming Language :: Python :: 3
Classifier: License :: OSI Approved :: MIT License
Classifier: Operating System :: OS Independent
Requires-Python: >=3.6
License-File: LICENSE.txt
